Metadata-Version: 2.1
Name: odoo12-addon-helpdesk-filter-mail-messages
Version: 12.0.1.0.2
Summary: Filter helpdesk ticket related messages by their type
Home-page: https://gitlab.com/somitcoop/erp-research/odoo-helpdesk
Author: Som It Cooperatiu SCCL, Som Connexió SCCL, Odoo Community Association (OCA)
Author-email: support@odoo-community.org
License: AGPL-3
Classifier: Programming Language :: Python
Classifier: Framework :: Odoo
Classifier: Framework :: Odoo :: 12.0
Classifier: License :: OSI Approved :: GNU Affero General Public License v3
Requires-Python: >=3.5
Requires-Dist: odoo12-addon-helpdesk-ticket-mail-message
Requires-Dist: odoo <12.1dev,>=12.0a
